{
    "APP": {
        "MAX_CPUS": 1,
        "REVIVE": false,
        "RES_DIR": "public/src",
        "LIB_DIR": "public/lib",
        "UPLOAD_DIR": "test/tmp"
    },

    "SERVER": {
        "PORT": 8080,
        "HOST": "http://127.0.0.1",
        "COOKIE": {
            "KEY": "key",
            "SECRET": "secret",
            "MAXAGE": 86400000
        }
    },

    "DATABASE": {

        "NAME": "database",
        "HOST": "localhost",
        "PORT": 27017,

        "USER": "root",
        "PASS": ""
    },

    "LOGGING": {
        "CONSOLE": {
            "ENABLED": true,
            "LEVEL": "silly"
        },
        "FILE": {
            "ENABLED": true,
            "LEVEL": "silly",
            "NAME": "output.log"
        }
    }
}
